LICENSE
MANIFEST.in
README.md
setup.py
pytube/__init__.py
pytube/__main__.py
pytube/captions.py
pytube/cipher.py
pytube/cli.py
pytube/exceptions.py
pytube/extract.py
pytube/helpers.py
pytube/innertube.py
pytube/itags.py
pytube/metadata.py
pytube/monostate.py
pytube/parser.py
pytube/query.py
pytube/request.py
pytube/streams.py
pytube/version.py
pytube/contrib/__init__.py
pytube/contrib/channel.py
pytube/contrib/playlist.py
pytube/contrib/search.py
pytubez.egg-info/PKG-INFO
pytubez.egg-info/SOURCES.txt
pytubez.egg-info/dependency_links.txt
pytubez.egg-info/entry_points.txt
pytubez.egg-info/top_level.txt
pytubez.egg-info/zip-safe
tests/__init__.py
tests/conftest.py
tests/test_captions.py
tests/test_cipher.py
tests/test_cli.py
tests/test_exceptions.py
tests/test_extract.py
tests/test_helpers.py
tests/test_itags.py
tests/test_main.py
tests/test_metadata.py
tests/test_parser.py
tests/test_query.py
tests/test_request.py
tests/test_streams.py
tests/contrib/test_channel.py
tests/contrib/test_playlist.py